sample_package_211031/__init__.py
sample_package_211031/sample/__init__.py
sample_package_211031/sample/sample.py
sample_package_211031-0.1.2.dist-info/WHEEL
sample_package_211031-0.1.2.dist-info/METADATA
sample_package_211031-0.1.2.dist-info/RECORD
