Metadata-Version: 2.1
Name: sample-package-211031
Version: 0.1.2
Summary: sample package
License: MIT
Author: Your Name
Author-email: you@example.com
Requires-Python: >=3.8,<4.0
Classifier: License :: OSI Approved :: MIT License
Classifier: Programming Language :: Python :: 3
Classifier: Programming Language :: Python :: 3.10
Classifier: Programming Language :: Python :: 3.8
Classifier: Programming Language :: Python :: 3.9
Requires-Dist: black (>=21.9b0,<22.0)
Requires-Dist: flake8 (>=4.0.1,<5.0.0)
Requires-Dist: jupyterlab (>=3.2.1,<4.0.0)
Requires-Dist: mypy (>=0.910,<0.911)
Requires-Dist: nbstripout (>=0.5.0,<0.6.0)
